ssdportal/__init__.py
ssdportal/config.py
ssdportal/contact.py
ssdportal/message.py
ssdportal/module.py
tests/__init__.py
tests/test_module.py
ssdportal-0.0.2.dist-info/LICENSE
ssdportal-0.0.2.dist-info/METADATA
ssdportal-0.0.2.dist-info/WHEEL
ssdportal-0.0.2.dist-info/top_level.txt
ssdportal-0.0.2.dist-info/RECORD
